qmemcalc/__init__.py
qmemcalc/memory.py
qmemcalc-0.1.1.dist-info/licenses/LICENSE
qmemcalc-0.1.1.dist-info/METADATA
qmemcalc-0.1.1.dist-info/WHEEL
qmemcalc-0.1.1.dist-info/entry_points.txt
qmemcalc-0.1.1.dist-info/top_level.txt
qmemcalc-0.1.1.dist-info/RECORD
