Metadata-Version: 2.4
Name: qmemcalc
Version: 0.1.1
Summary: GPU Memory Estimator for QLoRA / LoRA / Transformers
Home-page: https://github.com/sachin62025/qmemcalc
Author: Sachin
Author-email: sachin18449kumar@gmail.com
License: MIT
Classifier: Programming Language :: Python :: 3
Classifier: License :: OSI Approved :: MIT License
Classifier: Operating System :: OS Independent
Requires-Python: >=3.8
License-File: LICENSE
Requires-Dist: torch>=2.0
Requires-Dist: transformers>=4.40
Provides-Extra: dev
Requires-Dist: pytest; extra == "dev"
Dynamic: author
Dynamic: author-email
Dynamic: classifier
Dynamic: description
Dynamic: description-content-type
Dynamic: home-page
Dynamic: license
Dynamic: license-file
Dynamic: provides-extra
Dynamic: requires-dist
Dynamic: requires-python
Dynamic: summary
